autowire_decorator/__init__.py
autowire_decorator/autowire_decorator.py
autowire_decorator/model_api.py
autowire_decorator/parser_api.py
autowire_decorator/path_param.py
autowire_decorator-0.1.1.dist-info/WHEEL
autowire_decorator-0.1.1.dist-info/METADATA
autowire_decorator-0.1.1.dist-info/RECORD
