Metadata-Version: 2.1
Name: autowire-decorator
Version: 0.1.1
Summary: 
License: MIT
Author: nadaabdelmaboud
Author-email: nada5aled52@gmail.com
Requires-Python: >=3.7,<4.0
Classifier: License :: OSI Approved :: MIT License
Classifier: Programming Language :: Python :: 3
Classifier: Programming Language :: Python :: 3.7
Classifier: Programming Language :: Python :: 3.8
Classifier: Programming Language :: Python :: 3.9
Requires-Dist: flask-restx (>=0.5.0,<0.6.0)
